pytimeNSW/__init__.py
pytimeNSW/exception.py
pytimeNSW/filter.py
pytimeNSW/pytimeNSW.py
pytimeNSW-0.2.1.dist-info/DESCRIPTION.rst
pytimeNSW-0.2.1.dist-info/METADATA
pytimeNSW-0.2.1.dist-info/RECORD
pytimeNSW-0.2.1.dist-info/WHEEL
pytimeNSW-0.2.1.dist-info/metadata.json
pytimeNSW-0.2.1.dist-info/top_level.txt
