Metadata-Version: 2.0
Name: pytimeNSW
Version: 0.2.1
Summary: PyTime fork for NSW, Australia
Home-page: https://github.com/MatthewBurke1995/PyTimeNSW
Author: Matthew Burke
Author-email: mperoburke@gmail.com
License: MIT
Keywords: datetime time datetime timeparser Australia NSW holiday
Platform: UNKNOWN
Classifier: Intended Audience :: Developers
Classifier: License :: OSI Approved :: MIT License
Classifier: Operating System :: OS Independent
Classifier: Programming Language :: Python
Classifier: Programming Language :: Python :: 2.6
Classifier: Programming Language :: Python :: 2.7
Classifier: Programming Language :: Python :: 3.2
Classifier: Programming Language :: Python :: 3.3
Classifier: Programming Language :: Python :: 3.4
Classifier: Topic :: Software Development :: Libraries :: Python Modules
Classifier: Programming Language :: Python :: Implementation :: PyPy
Classifier: Programming Language :: Python :: Implementation :: CPython
